commbank_api_client/__init__.py
commbank_api_client/types.py
commbank_api_client-1.0.1.dist-info/LICENSE
commbank_api_client-1.0.1.dist-info/METADATA
commbank_api_client-1.0.1.dist-info/WHEEL
commbank_api_client-1.0.1.dist-info/top_level.txt
commbank_api_client-1.0.1.dist-info/RECORD
